[
   {
      "id": 1,
      "name": "Lieutenant_heart",
      "description": "Ida's favorite flower",
      "author": "placeholder1",
      "imageUrl": "HOSTNAME/assets/img/pic.jpg"
   },
   {
      "id": 2,
      "name": "placeholder2",
      "description": "placeholder2",
      "author": "placeholder2",
      "imageUrl": "HOSTNAME/assets/img/pic.jpg"
   },
   {
      "id": 3,
      "name": "placeholder2",
      "description": "placeholder2",
      "author": "placeholder2",
      "imageUrl": "HOSTNAME/assets/img/pic.jpg"
   },
   {
      "id": 4,
      "name": "placeholder2",
      "description": "placeholder2",
      "author": "placeholder2",
      "imageUrl": "HOSTNAME/assets/img/pic.jpg"
   }
]